easyaddition_quicklyfix/__init__.py
easyaddition_quicklyfix/module.py
easyaddition_quicklyfix-0.0.9.dist-info/METADATA
easyaddition_quicklyfix-0.0.9.dist-info/WHEEL
easyaddition_quicklyfix-0.0.9.dist-info/top_level.txt
easyaddition_quicklyfix-0.0.9.dist-info/RECORD
