Metadata-Version: 2.1
Name: easyaddition-quicklyfix
Version: 0.0.9
Summary: My first Python package
Home-page: UNKNOWN
Author: Saurabh Kumar
Author-email: saurabh.kumar@agatsa.com
License: UNKNOWN
Keywords: python,first package
Platform: UNKNOWN
Classifier: Development Status :: 3 - Alpha
Classifier: Intended Audience :: Education
Classifier: Programming Language :: Python :: 2
Classifier: Programming Language :: Python :: 3
Classifier: Operating System :: MacOS :: MacOS X
Classifier: Operating System :: Microsoft :: Windows
Requires-Dist: numpy
Requires-Dist: pandas
